{
  "map_match": {
    "pos": { "xy": [179, 889], "size": [313, 390]}
  },
  "factory": [
    {
      "offset": 2,
      "pos": {"xy": [65, 1329], "size": [112, 87] }
    },
    {
      "offset": 2,
      "pos": {"xy": [549, 1680], "size": [107, 63] }
    },
    {
      "offset": 2,
      "pos": {"xy": [897, 1329], "size": [122, 95] }
    },
    {
      "offset": 3,
      "pos": {"xy": [65, 1518], "size": [115, 105] }
    },
    {
      "offset": 3,
      "pos": {"xy": [902, 1517], "size": [126, 94] }
    }
  ]
}